svg/__init__.py
svg/node.py
svg/path.py
svg/style.py
svg/svg.py
svg/util.py
pysvglib-0.3.2.dist-info/LICENSE
pysvglib-0.3.2.dist-info/METADATA
pysvglib-0.3.2.dist-info/WHEEL
pysvglib-0.3.2.dist-info/top_level.txt
pysvglib-0.3.2.dist-info/RECORD
