Metadata-Version: 2.1
Name: pysvglib
Version: 0.3.2
Summary: SVG drawing library
Home-page: https://github.com/gbingersoll/pysvglib
Author: Greg Ingersoll
Author-email: greg.ingersoll@convolutionresearch.com
License: MIT
Keywords: svg graphics
Platform: UNKNOWN
Classifier: Development Status :: 4 - Beta
Classifier: License :: OSI Approved :: MIT License
Classifier: Programming Language :: Python :: 3
Classifier: Natural Language :: English
Classifier: Operating System :: OS Independent
Classifier: Topic :: Multimedia :: Graphics
Provides-Extra: dev
Requires-Dist: pytest ; extra == 'dev'
Requires-Dist: pycodestyle ; extra == 'dev'
Requires-Dist: setuptools ; extra == 'dev'
Requires-Dist: wheel ; extra == 'dev'
